theia/__init__.py
theia/py.typed
theia/client/__init__.py
theia/client/client.py
theia/core/__init__.py
theia/core/config.py
theia/core/primitives.py
theia/core/primitives_test.py
theia/core/test_mocks.py
theia/core/test_mocks_test.py
theia/core/timing.py
theia/core/timing_test.py
theia/core/web.py
theia_client-0.2.1.dist-info/METADATA
theia_client-0.2.1.dist-info/WHEEL
theia_client-0.2.1.dist-info/licenses/LICENSE
theia_client-0.2.1.dist-info/RECORD
