Metadata-Version: 2.4
Name: theia-client
Version: 0.2.1
Summary: Client package for Theia perception safety system.
Project-URL: Homepage, https://github.com/builtrobotics/gaia-theia
Author-email: Liam Osler <liam@builtrobotics.com>, Thomas Labourdette <thomas@builtrobotics.com>
License-Expression: MIT
License-File: LICENSE
Classifier: Operating System :: OS Independent
Classifier: Programming Language :: Python :: 3
Requires-Python: >=3.10
Requires-Dist: aiohttp~=3.11
